azure/mgmt/terraform/__init__.py
azure/mgmt/terraform/_client.py
azure/mgmt/terraform/_configuration.py
azure/mgmt/terraform/_model_base.py
azure/mgmt/terraform/_patch.py
azure/mgmt/terraform/_serialization.py
azure/mgmt/terraform/_version.py
azure/mgmt/terraform/py.typed
azure/mgmt/terraform/aio/__init__.py
azure/mgmt/terraform/aio/_client.py
azure/mgmt/terraform/aio/_configuration.py
azure/mgmt/terraform/aio/_patch.py
azure/mgmt/terraform/aio/operations/__init__.py
azure/mgmt/terraform/aio/operations/_operations.py
azure/mgmt/terraform/aio/operations/_patch.py
azure/mgmt/terraform/models/__init__.py
azure/mgmt/terraform/models/_enums.py
azure/mgmt/terraform/models/_models.py
azure/mgmt/terraform/models/_patch.py
azure/mgmt/terraform/operations/__init__.py
azure/mgmt/terraform/operations/_operations.py
azure/mgmt/terraform/operations/_patch.py
azure_mgmt_terraform-1.0.0b1.dist-info/LICENSE
azure_mgmt_terraform-1.0.0b1.dist-info/METADATA
azure_mgmt_terraform-1.0.0b1.dist-info/WHEEL
azure_mgmt_terraform-1.0.0b1.dist-info/top_level.txt
azure_mgmt_terraform-1.0.0b1.dist-info/RECORD
